{
  "name": "NinanceSwap Default List",
  "timestamp": "2021-05-06T00:00:00Z",
  "version": {
    "major": 3,
    "minor": 0,
    "patch": 0
  },
  "tags": {},
  "logoURI": "https://pancakeswap.finance/logo.png",
  "keywords": ["pancake", "default"],
  "tokens": [
    {
      "name": "WBNB Token",
      "symbol": "WBNB",
      "address": "0xbb4CdB9CBd36B01bD1cBaEBF2De08d9173bc095c",
      "chainId": 56,
      "decimals": 18,
      "logoURI": "https://pancakeswap.finance/images/tokens/0xbb4cdb9cbd36b01bd1cbaebf2de08d9173bc095c.png"
    },

    {
      "name": "Tether USD",
      "symbol": "USDT",
      "address": "0x55d398326f99059fF775485246999027B3197955",
      "chainId": 56,
      "decimals": 18,
      "logoURI": "https://pancakeswap.finance/images/tokens/0x55d398326f99059ff775485246999027b3197955.png"
    },
    {
      "name": "Ninance Token",
      "symbol": "ERA(old)",
      "address": "0xa3a9d092f40d2642b1dbaceb5df6b0c7940f9ab4",
      "chainId": 56,
      "decimals": 18,
      "logoURI": "https://www.ninance.io/static/era-logo.c6a5cb3c.svg"
    },
    {
      "name": "Ninance Token",
      "symbol": "ERA",
      "address": "0x3f47D316b6Ca268C8a7916D6Ed02E90DbFEE3EE2",
      "chainId": 56,
      "decimals": 18,
      "logoURI": "https://www.ninance.io/static/era-logo.c6a5cb3c.svg"
    }
  ]
}
